{"is_source_file": true, "format": "JavaScript (React JSX)", "description": "This file defines a React functional component called Hero, which renders a hero section with a headline and subtitle for a web application's frontend.", "external_files": ["./Hero.css"], "external_methods": [], "published": ["default"], "classes": [], "methods": [{"name": "Hero()", "description": "React functional component rendering a hero section with title and subtitle.", "scope": "", "scopeKind": ""}], "calls": ["React", "React.createElement"], "search-terms": ["Hero component", "React JSX", "frontend hero section", "SOW platform", "UI component"], "state": 2, "file_id": 31, "knowledge_revision": 203, "git_revision": "2c2b137b5481927e81fd6036bc6f8f7e2a4948d8", "revision_history": [{"66": ""}, {"196": "2c2b137b5481927e81fd6036bc6f8f7e2a4948d8"}, {"203": "2c2b137b5481927e81fd6036bc6f8f7e2a4948d8"}], "ctags": [{"_type": "tag", "name": "Hero", "path": "/home/kavia/workspace/code-generation/sow-generator-platform-17223-17232/frontend_reactjs/src/components/Hero.jsx", "pattern": "/^export default function Hero() {$/", "language": "JavaScript", "kind": "function", "signature": "()"}], "hash": "cff6417eb8d97ccb2df77ba6556626b5", "format-version": 4, "code-base-name": "frontend_reactjs", "filename": "frontend_reactjs/src/components/Hero.jsx"}